{
  "products": [
    {
      "id": "926f",
      "name": "Chinola ",
      "price": 25
    },
    {
      "id": "2815",
      "name": "Habichuela Roja 1lbs",
      "price": 75
    },
    {
      "id": "946e",
      "name": "Guandules secos 1lbs",
      "price": 85
    },
    {
      "id": "3d44",
      "name": "Caña",
      "price": 100
    },
    {
      "id": "6470",
      "name": "Azucar 1Lbs",
      "price": 40
    }
  ],
  "inventories": [
    {
      "id": "3evwkno6q",
      "name": "Inventario octubre 2",
      "products": []
    },
    {
      "id": "xifvpu8at",
      "name": "Inventario octubre 3",
      "products": [
        {
          "id": "6470",
          "name": "Azucar 1Lbs",
          "price": 40
        }
      ]
    }
  ]
}